akitir_textutils-0.1.0.dist-info/licenses/LICENSE
textutils/__init__.py
textutils/core.py
textutils/formatters.py
textutils/validators.py
akitir_textutils-0.1.0.dist-info/METADATA
akitir_textutils-0.1.0.dist-info/WHEEL
akitir_textutils-0.1.0.dist-info/entry_points.txt
akitir_textutils-0.1.0.dist-info/top_level.txt
akitir_textutils-0.1.0.dist-info/RECORD
