Metadata-Version: 2.4
Name: akitir-textutils
Version: 0.1.0
Summary: A comprehensive text processing utility library
Author-email: Your Name <your.email@example.com>
License: MIT License
Project-URL: Homepage, https://github.com/yourusername/akitir-textutils
Project-URL: Bug Reports, https://github.com/yourusername/akitir-textutils/issues
Project-URL: Source, https://github.com/yourusername/akitir-textutils
Project-URL: Documentation, https://textutils.readthedocs.io/
Keywords: text,processing,utilities,string,validation
Classifier: Development Status :: 4 - Beta
Classifier: Intended Audience :: Developers
Classifier: License :: OSI Approved :: MIT License
Classifier: Operating System :: OS Independent
Classifier: Programming Language :: Python :: 3
Classifier: Programming Language :: Python :: 3.7
Classifier: Programming Language :: Python :: 3.8
Classifier: Programming Language :: Python :: 3.9
Classifier: Programming Language :: Python :: 3.10
Classifier: Programming Language :: Python :: 3.11
Classifier: Topic :: Software Development :: Libraries :: Python Modules
Classifier: Topic :: Text Processing
Requires-Python: >=3.7
License-File: LICENSE
Requires-Dist: black>=23.3.0
Requires-Dist: build>=1.1.1
Requires-Dist: flake8>=3.9.2
Requires-Dist: mypy>=1.4.1
Requires-Dist: pytest>=7.4.4
Requires-Dist: pytest-cov>=4.1.0
Requires-Dist: setuptools>=68.0.0
Requires-Dist: sphinx>=5.3.0
Requires-Dist: sphinx-rtd-theme>=2.0.0
Requires-Dist: twine>=4.0.2
Provides-Extra: dev
Requires-Dist: pytest>=6.0; extra == "dev"
Requires-Dist: pytest-cov>=2.0; extra == "dev"
Requires-Dist: black>=21.0; extra == "dev"
Requires-Dist: flake8>=3.8; extra == "dev"
Requires-Dist: mypy>=0.900; extra == "dev"
Provides-Extra: docs
Requires-Dist: sphinx>=4.0; extra == "docs"
Requires-Dist: sphinx-rtd-theme>=1.0; extra == "docs"
Dynamic: license-file
